{
  "meta": {
    "data_version": "1.1.0",
    "created": "2023-10-27",
    "revision": 1
  },
  "info": {
    "balls_per_over": 6,
    "city": "Jaipur",
    "dates": [
      "2023-10-25"
    ],
    "event": {
      "name": "Syed Mushtaq Ali Trophy",
      "group": "A"
    },
    "gender": "male",
    "match_type": "T20",
    "officials": {
      "match_referees": [
        "P Dharmani"
      ],
      "umpires": [
        "M Kuppuraj",
        "GR Sadashiv Iyer"
      ]
    },
    "outcome": {
      "winner": "Baroda",
      "by": {
        "wickets": 7
      }
    },
    "overs": 20,
    "players": {
      "Chhattisgarh": [
        "Sanidhya Hurkat",
        "Amandeep Khare",
        "Harpreet Singh",
        "Shashank Singh",
        "Ajay Mandal",
        "Eknath Kerkar",
        "Shashank Chandrakar",
        "Sanjeet Desai",
        "SS Agarwal",
        "PS Painkra",
        "Sumit Ruikar",
        "Sourabh Majumdar"
      ],
      "Baroda": [
        "SI Sopariya",
        "Jyotsnil Singh",
        "A Bharwad",
        "KH Pandya",
        "Vishnu Solanki",
        "Bhanu Pania",
        "AV Rajput",
        "SS Sharma",
        "A Sheth",
        "NA Rathva",
        "LI Meriwala",
        "MV Pithiya"
      ]
    },
    "registry": {
      "people": {
        "A Bharwad": "3cc96a05",
        "A Sheth": "4312e8f9",
        "AV Rajput": "c1d3515b",
        "Ajay Mandal": "31ee319e",
        "Amandeep Khare": "6c6cc94c",
        "Bhanu Pania": "af863475",
        "Eknath Kerkar": "84085032",
        "GR Sadashiv Iyer": "0be62e31",
        "Harpreet Singh": "28c78fb3",
        "Jyotsnil Singh": "b32b1661",
        "KH Pandya": "5b8c830e",
        "LI Meriwala": "d3611425",
        "M Kuppuraj": "aa4063d0",
        "MV Pithiya": "1c29d51f",
        "NA Rathva": "8f607eea",
        "P Dharmani": "eaa90ab4",
        "PS Painkra": "6cdc3215",
        "SI Sopariya": "d477678c",
        "SS Agarwal": "b51f72a5",
        "SS Sharma": "0ebaa16a",
        "Sanidhya Hurkat": "083c2d59",
        "Sanjeet Desai": "9b0d5e52",
        "Shashank Chandrakar": "9c20688d",
        "Shashank Singh": "26989d80",
        "Sourabh Majumdar": "30225730",
        "Sumit Ruikar": "f4ef0fd7",
        "Vishnu Solanki": "2e802011"
      }
    },
    "season": "2023/24",
    "team_type": "club",
    "teams": [
      "Chhattisgarh",
      "Baroda"
    ],
    "toss": {
      "decision": "field",
      "winner": "Baroda"
    },
    "venue": "Sawai Mansingh Stadium, Jaipur"
  },
  "innings": [
    {
      "team": "Chhattisgarh",
      "overs": [
        {
          "over": 0,
          "deliveries": [
            {
              "batter": "Sanidhya Hurkat",
              "bowler": "SI Sopariya",
              "non_striker": "Amandeep Khare",
              "runs": {
                "batter": 0,
                "extras": 0,
                "total": 0
              }
            },
            {
              "batter": "Sanidhya Hurkat",
              "bowler": "SI Sopariya",
              "non_striker": "Amandeep Khare",
              "runs": {
                "batter": 0,
                "extras": 0,
                "total": 0
              }
            },
            {
              "batter": "Sanidhya Hurkat",
              "bowler": "SI Sopariya",
              "non_striker": "Amandeep Khare",
              "runs": {
                "batter": 1,
                "extras": 0,
                "total": 1
              }
            },
            {
              "batter": "Amandeep Khare",
              "bowler": "SI Sopariya",
              "non_striker": "Sanidhya Hurkat",
              "runs": {
                "batter": 0,
                "extras": 0,
                "total": 0
              }
            },
            {
              "batter": "Amandeep Khare",
              "bowler": "SI Sopariya",
              "non_striker": "Sanidhya Hurkat",
              "runs": {
                "batter": 0,
                "extras": 0,
                "total": 0
              }
            },
            {
              "batter": "Amandeep Khare",
              "bowler": "SI Sopariya",
              "non_striker": "Sanidhya Hurkat",
              "runs": {
                "batter": 0,
                "extras": 0,
                "total": 0
              }
            }
          ]
        },
        {
          "over": 1,
          "deliveries": [
            {
              "batter": "Sanidhya Hurkat",
              "bowler": "A Sheth",
              "extras": {
                "wides": 1
              },
              "non_striker": "Amandeep Khare",
              "runs": {
                "batter": 0,
                "extras": 1,
                "total": 1
              }
            },
            {
              "batter": "Sanidhya Hurkat",
              "bowler": "A Sheth",
              "non_striker": "Amandeep Khare",
              "runs": {
                "batter": 4,
                "extras": 0,
                "total": 4
              }
            },
            {
              "batter": "Sanidhya Hurkat",
              "bowler": "A Sheth",
              "non_striker": "Amandeep Khare",
              "runs": {
                "batter": 1,
                "extras": 0,
                "total": 1
              }
            },
            {
              "batter": "Amandeep Khare",
              "bowler": "A Sheth",
              "non_striker": "Sanidhya Hurkat",
              "runs": {
                "batter": 1,
                "extras": 0,
                "total": 1
              }
            },
            {
              "batter": "Sanidhya Hurkat",
              "bowler": "A Sheth",
              "non_striker": "Amandeep Khare",
              "runs": {
                "batter": 0,
                "extras": 0,
                "total": 0
              }
            },
            {
              "batter": "Sanidhya Hurkat",
              "bowler": "A Sheth",
              "non_striker": "Amandeep Khare",
              "runs": {
                "batter": 1,
                "extras": 0,
                "total": 1
              }
            },
            {
              "batter": "Amandeep Khare",
              "bowler": "A Sheth",
              "non_striker": "Sanidhya Hurkat",
              "runs": {
                "batter": 1,
                "extras": 0,
                "total": 1
              }
            }
          ]
        },
        {
          "over": 2,
          "deliveries": [
            {
              "batter": "Amandeep Khare",
              "bowler": "SI Sopariya",
              "non_striker": "Sanidhya Hurkat",
              "runs": {
                "batter": 0,
                "extras": 0,
                "total": 0
              }
            },
            {
              "batter": "Amandeep Khare",
              "bowler": "SI Sopariya",
              "non_striker": "Sanidhya Hurkat",
              "runs": {
                "batter": 1,
                "extras": 0,
                "total": 1
              }
            },
            {
              "batter": "Sanidhya Hurkat",
              "bowler": "SI Sopariya",
              "non_striker": "Amandeep Khare",
              "runs": {
                "batter": 1,
                "extras": 0,
                "total": 1
              }
            },
            {
              "batter": "Amandeep Khare",
              "bowler": "SI Sopariya",
              "non_striker": "Sanidhya Hurkat",
              "runs": {
                "batter": 0,
                "extras": 0,
                "total": 0
              }
            },
            {
              "batter": "Amandeep Khare",
              "bowler": "SI Sopariya",
              "non_striker": "Sanidhya Hurkat",
              "runs": {
                "batter": 0,
                "extras": 0,
                "total": 0
              }
            },
            {
              "batter": "Amandeep Khare",
              "bowler": "SI Sopariya",
              "non_striker": "Sanidhya Hurkat",
              "runs": {
                "batter": 0,
                "extras": 0,
                "total": 0
              }
            }
          ]
        },
        {
          "over": 3,
          "deliveries": [
            {
              "batter": "Sanidhya Hurkat",
              "bowler": "LI Meriwala",
              "non_striker": "Amandeep Khare",
              "runs": {
                "batter": 0,
                "extras": 0,
                "total": 0
              }
            },
            {
              "batter": "Sanidhya Hurkat",
              "bowler": "LI Meriwala",
              "non_striker": "Amandeep Khare",
              "runs": {
                "batter": 1,
                "extras": 0,
                "total": 1
              }
            },
            {
              "batter": "Amandeep Khare",
              "bowler": "LI Meriwala",
              "non_striker": "Sanidhya Hurkat",
              "runs": {
                "batter": 0,
                "extras": 0,
                "total": 0
              }
            },
            {
              "batter": "Amandeep Khare",
              "bowler": "LI Meriwala",
              "non_striker": "Sanidhya Hurkat",
              "runs": {
                "batter": 2,
                "extras": 0,
                "total": 2
              }
            },
            {
              "batter": "Amandeep Khare",
              "bowler": "LI Meriwala",
              "non_striker": "Sanidhya Hurkat",
              "runs": {
                "batter": 0,
                "extras": 0,
                "total": 0
              }
            },
            {
              "batter": "Amandeep Khare",
              "bowler": "LI Meriwala",
              "non_striker": "Sanidhya Hurkat",
              "runs": {
                "batter": 1,
                "extras": 0,
                "total": 1
              }
            }
          ]
        },
        {
          "over": 4,
          "deliveries": [
            {
              "batter": "Amandeep Khare",
              "bowler": "KH Pandya",
              "non_striker": "Sanidhya Hurkat",
              "runs": {
                "batter": 1,
                "extras": 0,
                "total": 1
              }
            },
            {
              "batter": "Sanidhya Hurkat",
              "bowler": "KH Pandya",
              "non_striker": "Amandeep Khare",
              "runs": {
                "batter": 1,
                "extras": 0,
                "total": 1
              }
            },
            {
              "batter": "Amandeep Khare",
              "bowler": "KH Pandya",
              "non_striker": "Sanidhya Hurkat",
              "runs": {
                "batter": 6,
                "extras": 0,
                "total": 6
              }
            },
            {
              "batter": "Amandeep Khare",
              "bowler": "KH Pandya",
              "non_striker": "Sanidhya Hurkat",
              "runs": {
                "batter": 0,
                "extras": 0,
                "total": 0
              }
            },
            {
              "batter": "Amandeep Khare",
              "bowler": "KH Pandya",
              "non_striker": "Sanidhya Hurkat",
              "runs": {
                "batter": 1,
                "extras": 0,
                "total": 1
              }
            },
            {
              "batter": "Sanidhya Hurkat",
              "bowler": "KH Pandya",
              "extras": {
                "wides": 1
              },
              "non_striker": "Amandeep Khare",
              "runs": {
                "batter": 0,
                "extras": 1,
                "total": 1
              }
            },
            {
              "batter": "Sanidhya Hurkat",
              "bowler": "KH Pandya",
              "non_striker": "Amandeep Khare",
              "runs": {
                "batter": 4,
                "extras": 0,
                "total": 4
              }
            }
          ]
        },
        {
          "over": 5,
          "deliveries": [
            {
              "batter": "Amandeep Khare",
              "bowler": "LI Meriwala",
              "non_striker": "Sanidhya Hurkat",
              "runs": {
                "batter": 0,
                "extras": 0,
                "total": 0
              }
            },
            {
              "batter": "Amandeep Khare",
              "bowler": "LI Meriwala",
              "non_striker": "Sanidhya Hurkat",
              "runs": {
                "batter": 1,
                "extras": 0,
                "total": 1
              }
            },
            {
              "batter": "Sanidhya Hurkat",
              "bowler": "LI Meriwala",
              "non_striker": "Amandeep Khare",
              "runs": {
                "batter": 0,
                "extras": 0,
                "total": 0
              },
              "wickets": [
                {
                  "player_out": "Sanidhya Hurkat",
                  "fielders": [
                    {
                      "name": "KH Pandya"
                    }
                  ],
                  "kind": "caught"
                }
              ]
            },
            {
              "batter": "Harpreet Singh",
              "bowler": "LI Meriwala",
              "non_striker": "Amandeep Khare",
              "runs": {
                "batter": 1,
                "extras": 0,
                "total": 1
              }
            },
            {
              "batter": "Amandeep Khare",
              "bowler": "LI Meriwala",
              "non_striker": "Harpreet Singh",
              "runs": {
                "batter": 0,
                "extras": 0,
                "total": 0
              }
            },
            {
              "batter": "Amandeep Khare",
              "bowler": "LI Meriwala",
              "non_striker": "Harpreet Singh",
              "runs": {
                "batter": 1,
                "extras": 0,
                "total": 1
              }
            }
          ]
        },
        {
          "over": 6,
          "deliveries": [
            {
              "batter": "Amandeep Khare",
              "bowler": "KH Pandya",
              "non_striker": "Harpreet Singh",
              "runs": {
                "batter": 1,
                "extras": 0,
                "total": 1
              }
            },
            {
              "batter": "Harpreet Singh",
              "bowler": "KH Pandya",
              "non_striker": "Amandeep Khare",
              "runs": {
                "batter": 1,
                "extras": 0,
                "total": 1
              }
            },
            {
              "batter": "Amandeep Khare",
              "bowler": "KH Pandya",
              "non_striker": "Harpreet Singh",
              "runs": {
                "batter": 0,
                "extras": 0,
                "total": 0
              }
            },
            {
              "batter": "Amandeep Khare",
              "bowler": "KH Pandya",
              "non_striker": "Harpreet Singh",
              "runs": {
                "batter": 1,
                "extras": 0,
                "total": 1
              }
            },
            {
              "batter": "Harpreet Singh",
              "bowler": "KH Pandya",
              "non_striker": "Amandeep Khare",
              "runs": {
                "batter": 0,
                "extras": 0,
                "total": 0
              }
            },
            {
              "batter": "Harpreet Singh",
              "bowler": "KH Pandya",
              "non_striker": "Amandeep Khare",
              "runs": {
                "batter": 0,
                "extras": 0,
                "total": 0
              }
            }
          ]
        },
        {
          "over": 7,
          "deliveries": [
            {
              "batter": "Amandeep Khare",
              "bowler": "MV Pithiya",
              "non_striker": "Harpreet Singh",
              "runs": {
                "batter": 1,
                "extras": 0,
                "total": 1
              }
            },
            {
              "batter": "Harpreet Singh",
              "bowler": "MV Pithiya",
              "non_striker": "Amandeep Khare",
              "runs": {
                "batter": 0,
                "extras": 0,
                "total": 0
              }
            },
            {
              "batter": "Harpreet Singh",
              "bowler": "MV Pithiya",
              "non_striker": "Amandeep Khare",
              "runs": {
                "batter": 0,
                "extras": 0,
                "total": 0
              }
            },
            {
              "batter": "Harpreet Singh",
              "bowler": "MV Pithiya",
              "non_striker": "Amandeep Khare",
              "runs": {
                "batter": 1,
                "extras": 0,
                "total": 1
              }
            },
            {
              "batter": "Amandeep Khare",
              "bowler": "MV Pithiya",
              "non_striker": "Harpreet Singh",
              "runs": {
                "batter": 1,
                "extras": 0,
                "total": 1
              }
            },
            {
              "batter": "Harpreet Singh",
              "bowler": "MV Pithiya",
              "non_striker": "Amandeep Khare",
              "runs": {
                "batter": 2,
                "extras": 0,
                "total": 2
              }
            }
          ]
        },
        {
          "over": 8,
          "deliveries": [
            {
              "batter": "Amandeep Khare",
              "bowler": "KH Pandya",
              "non_striker": "Harpreet Singh",
              "runs": {
                "batter": 1,
                "extras": 0,
                "total": 1
              }
            },
            {
              "batter": "Harpreet Singh",
              "bowler": "KH Pandya",
              "non_striker": "Amandeep Khare",
              "runs": {
                "batter": 1,
                "extras": 0,
                "total": 1
              }
            },
            {
              "batter": "Amandeep Khare",
              "bowler": "KH Pandya",
              "non_striker": "Harpreet Singh",
              "runs": {
                "batter": 0,
                "extras": 0,
                "total": 0
              }
            },
            {
              "batter": "Amandeep Khare",
              "bowler": "KH Pandya",
              "non_striker": "Harpreet Singh",
              "runs": {
                "batter": 1,
                "extras": 0,
                "total": 1
              }
            },
            {
              "batter": "Harpreet Singh",
              "bowler": "KH Pandya",
              "non_striker": "Amandeep Khare",
              "runs": {
                "batter": 1,
                "extras": 0,
                "total": 1
              }
            },
            {
              "batter": "Amandeep Khare",
              "bowler": "KH Pandya",
              "extras": {
                "wides": 1
              },
              "non_striker": "Harpreet Singh",
              "runs": {
                "batter": 0,
                "extras": 1,
                "total": 1
              }
            },
            {
              "batter": "Amandeep Khare",
              "bowler": "KH Pandya",
              "non_striker": "Harpreet Singh",
              "runs": {
                "batter": 0,
                "extras": 0,
                "total": 0
              }
            }
          ]
        },
        {
          "over": 9,
          "deliveries": [
            {
              "batter": "Harpreet Singh",
              "bowler": "A Sheth",
              "non_striker": "Amandeep Khare",
              "runs": {
                "batter": 1,
                "extras": 0,
                "total": 1
              }
            },
            {
              "batter": "Amandeep Khare",
              "bowler": "A Sheth",
              "non_striker": "Harpreet Singh",
              "runs": {
                "batter": 0,
                "extras": 0,
                "total": 0
              },
              "wickets": [
                {
                  "player_out": "Amandeep Khare",
                  "fielders": [
                    {
                      "name": "A Bharwad"
                    }
                  ],
                  "kind": "caught"
                }
              ]
            },
            {
              "batter": "Shashank Singh",
              "bowler": "A Sheth",
              "non_striker": "Harpreet Singh",
              "runs": {
                "batter": 1,
                "extras": 0,
                "total": 1
              }
            },
            {
              "batter": "Harpreet Singh",
              "bowler": "A Sheth",
              "non_striker": "Shashank Singh",
              "runs": {
                "batter": 4,
                "extras": 0,
                "total": 4
              }
            },
            {
              "batter": "Harpreet Singh",
              "bowler": "A Sheth",
              "non_striker": "Shashank Singh",
              "runs": {
                "batter": 1,
                "extras": 0,
                "total": 1
              }
            },
            {
              "batter": "Shashank Singh",
              "bowler": "A Sheth",
              "non_striker": "Harpreet Singh",
              "runs": {
                "batter": 0,
                "extras": 0,
                "total": 0
              }
            }
          ]
        },
        {
          "over": 10,
          "deliveries": [
            {
              "batter": "Harpreet Singh",
              "bowler": "AV Rajput",
              "non_striker": "Shashank Singh",
              "runs": {
                "batter": 1,
                "extras": 0,
                "total": 1
              }
            },
            {
              "batter": "Shashank Singh",
              "bowler": "AV Rajput",
              "non_striker": "Harpreet Singh",
              "runs": {
                "batter": 1,
                "extras": 0,
                "total": 1
              }
            },
            {
              "batter": "Harpreet Singh",
              "bowler": "AV Rajput",
              "non_striker": "Shashank Singh",
              "runs": {
                "batter": 1,
                "extras": 0,
                "total": 1
              }
            },
            {
              "batter": "Shashank Singh",
              "bowler": "AV Rajput",
              "non_striker": "Harpreet Singh",
              "runs": {
                "batter": 0,
                "extras": 0,
                "total": 0
              }
            },
            {
              "batter": "Shashank Singh",
              "bowler": "AV Rajput",
              "non_striker": "Harpreet Singh",
              "runs": {
                "batter": 1,
                "extras": 0,
                "total": 1
              }
            },
            {
              "batter": "Harpreet Singh",
              "bowler": "AV Rajput",
              "non_striker": "Shashank Singh",
              "runs": {
                "batter": 1,
                "extras": 0,
                "total": 1
              }
            }
          ]
        },
        {
          "over": 11,
          "deliveries": [
            {
              "batter": "Harpreet Singh",
              "bowler": "SI Sopariya",
              "non_striker": "Shashank Singh",
              "runs": {
                "batter": 1,
                "extras": 0,
                "total": 1
              }
            },
            {
              "batter": "Shashank Singh",
              "bowler": "SI Sopariya",
              "non_striker": "Harpreet Singh",
              "runs": {
                "batter": 1,
                "extras": 0,
                "total": 1
              }
            },
            {
              "batter": "Harpreet Singh",
              "bowler": "SI Sopariya",
              "non_striker": "Shashank Singh",
              "runs": {
                "batter": 0,
                "extras": 0,
                "total": 0
              }
            },
            {
              "batter": "Harpreet Singh",
              "bowler": "SI Sopariya",
              "non_striker": "Shashank Singh",
              "runs": {
                "batter": 1,
                "extras": 0,
                "total": 1
              }
            },
            {
              "batter": "Shashank Singh",
              "bowler": "SI Sopariya",
              "non_striker": "Harpreet Singh",
              "runs": {
                "batter": 2,
                "extras": 0,
                "total": 2
              }
            },
            {
              "batter": "Shashank Singh",
              "bowler": "SI Sopariya",
              "non_striker": "Harpreet Singh",
              "runs": {
                "batter": 1,
                "extras": 0,
                "total": 1
              }
            }
          ]
        },
        {
          "over": 12,
          "deliveries": [
            {
              "batter": "Shashank Singh",
              "bowler": "AV Rajput",
              "non_striker": "Harpreet Singh",
              "runs": {
                "batter": 1,
                "extras": 0,
                "total": 1
              }
            },
            {
              "batter": "Harpreet Singh",
              "bowler": "AV Rajput",
              "extras": {
                "legbyes": 1
              },
              "non_striker": "Shashank Singh",
              "runs": {
                "batter": 0,
                "extras": 1,
                "total": 1
              }
            },
            {
              "batter": "Shashank Singh",
              "bowler": "AV Rajput",
              "non_striker": "Harpreet Singh",
              "runs": {
                "batter": 1,
                "extras": 0,
                "total": 1
              }
            },
            {
              "batter": "Harpreet Singh",
              "bowler": "AV Rajput",
              "extras": {
                "wides": 1
              },
              "non_striker": "Shashank Singh",
              "runs": {
                "batter": 0,
                "extras": 1,
                "total": 1
              }
            },
            {
              "batter": "Harpreet Singh",
              "bowler": "AV Rajput",
              "non_striker": "Shashank Singh",
              "runs": {
                "batter": 4,
                "extras": 0,
                "total": 4
              }
            },
            {
              "batter": "Harpreet Singh",
              "bowler": "AV Rajput",
              "non_striker": "Shashank Singh",
              "runs": {
                "batter": 1,
                "extras": 0,
                "total": 1
              }
            },
            {
              "batter": "Shashank Singh",
              "bowler": "AV Rajput",
              "non_striker": "Harpreet Singh",
              "runs": {
                "batter": 4,
                "extras": 0,
                "total": 4
              }
            }
          ]
        },
        {
          "over": 13,
          "deliveries": [
            {
              "batter": "Harpreet Singh",
              "bowler": "SI Sopariya",
              "non_striker": "Shashank Singh",
              "runs": {
                "batter": 4,
                "extras": 0,
                "total": 4
              }
            },
            {
              "batter": "Harpreet Singh",
              "bowler": "SI Sopariya",
              "non_striker": "Shashank Singh",
              "runs": {
                "batter": 1,
                "extras": 0,
                "total": 1
              }
            },
            {
              "batter": "Shashank Singh",
              "bowler": "SI Sopariya",
              "non_striker": "Harpreet Singh",
              "runs": {
                "batter": 0,
                "extras": 0,
                "total": 0
              }
            },
            {
              "batter": "Shashank Singh",
              "bowler": "SI Sopariya",
              "non_striker": "Harpreet Singh",
              "runs": {
                "batter": 1,
                "extras": 0,
                "total": 1
              }
            },
            {
              "batter": "Harpreet Singh",
              "bowler": "SI Sopariya",
              "non_striker": "Shashank Singh",
              "runs": {
                "batter": 4,
                "extras": 0,
                "total": 4
              }
            },
            {
              "batter": "Harpreet Singh",
              "bowler": "SI Sopariya",
              "non_striker": "Shashank Singh",
              "runs": {
                "batter": 2,
                "extras": 0,
                "total": 2
              }
            }
          ]
        },
        {
          "over": 14,
          "deliveries": [
            {
              "batter": "Shashank Singh",
              "bowler": "KH Pandya",
              "non_striker": "Harpreet Singh",
              "replacements": {
                "match": [
                  {
                    "in": "NA Rathva",
                    "out": "SI Sopariya",
                    "team": "Baroda",
                    "reason": "impact_player"
                  }
                ]
              },
              "runs": {
                "batter": 1,
                "extras": 0,
                "total": 1
              }
            },
            {
              "batter": "Harpreet Singh",
              "bowler": "KH Pandya",
              "non_striker": "Shashank Singh",
              "runs": {
                "batter": 0,
                "extras": 0,
                "total": 0
              },
              "wickets": [
                {
                  "player_out": "Harpreet Singh",
                  "fielders": [
                    {
                      "name": "Jyotsnil Singh"
                    }
                  ],
                  "kind": "caught"
                }
              ]
            },
            {
              "batter": "Ajay Mandal",
              "bowler": "KH Pandya",
              "non_striker": "Shashank Singh",
              "runs": {
                "batter": 0,
                "extras": 0,
                "total": 0
              }
            },
            {
              "batter": "Ajay Mandal",
              "bowler": "KH Pandya",
              "non_striker": "Shashank Singh",
              "runs": {
                "batter": 0,
                "extras": 0,
                "total": 0
              }
            },
            {
              "batter": "Ajay Mandal",
              "bowler": "KH Pandya",
              "non_striker": "Shashank Singh",
              "runs": {
                "batter": 0,
                "extras": 0,
                "total": 0
              }
            },
            {
              "batter": "Ajay Mandal",
              "bowler": "KH Pandya",
              "non_striker": "Shashank Singh",
              "runs": {
                "batter": 1,
                "extras": 0,
                "total": 1
              }
            }
          ]
        },
        {
          "over": 15,
          "deliveries": [
            {
              "batter": "Ajay Mandal",
              "bowler": "NA Rathva",
              "non_striker": "Shashank Singh",
              "runs": {
                "batter": 1,
                "extras": 0,
                "total": 1
              }
            },
            {
              "batter": "Shashank Singh",
              "bowler": "NA Rathva",
              "non_striker": "Ajay Mandal",
              "runs": {
                "batter": 6,
                "extras": 0,
                "total": 6
              }
            },
            {
              "batter": "Shashank Singh",
              "bowler": "NA Rathva",
              "non_striker": "Ajay Mandal",
              "runs": {
                "batter": 1,
                "extras": 0,
                "total": 1
              }
            },
            {
              "batter": "Ajay Mandal",
              "bowler": "NA Rathva",
              "non_striker": "Shashank Singh",
              "runs": {
                "batter": 0,
                "extras": 0,
                "total": 0
              }
            },
            {
              "batter": "Ajay Mandal",
              "bowler": "NA Rathva",
              "non_striker": "Shashank Singh",
              "runs": {
                "batter": 1,
                "extras": 0,
                "total": 1
              }
            },
            {
              "batter": "Shashank Singh",
              "bowler": "NA Rathva",
              "non_striker": "Ajay Mandal",
              "runs": {
                "batter": 1,
                "extras": 0,
                "total": 1
              }
            }
          ]
        },
        {
          "over": 16,
          "deliveries": [
            {
              "batter": "Shashank Singh",
              "bowler": "A Sheth",
              "non_striker": "Ajay Mandal",
              "runs": {
                "batter": 1,
                "extras": 0,
                "total": 1
              }
            },
            {
              "batter": "Ajay Mandal",
              "bowler": "A Sheth",
              "non_striker": "Shashank Singh",
              "runs": {
                "batter": 1,
                "extras": 0,
                "total": 1
              }
            },
            {
              "batter": "Shashank Singh",
              "bowler": "A Sheth",
              "non_striker": "Ajay Mandal",
              "runs": {
                "batter": 1,
                "extras": 0,
                "total": 1
              }
            },
            {
              "batter": "Ajay Mandal",
              "bowler": "A Sheth",
              "non_striker": "Shashank Singh",
              "runs": {
                "batter": 0,
                "extras": 0,
                "total": 0
              },
              "wickets": [
                {
                  "player_out": "Ajay Mandal",
                  "fielders": [
                    {
                      "name": "SS Sharma"
                    }
                  ],
                  "kind": "caught"
                }
              ]
            },
            {
              "batter": "Eknath Kerkar",
              "bowler": "A Sheth",
              "non_striker": "Shashank Singh",
              "runs": {
                "batter": 4,
                "extras": 0,
                "total": 4
              }
            },
            {
              "batter": "Eknath Kerkar",
              "bowler": "A Sheth",
              "non_striker": "Shashank Singh",
              "runs": {
                "batter": 1,
                "extras": 0,
                "total": 1
              }
            }
          ]
        },
        {
          "over": 17,
          "deliveries": [
            {
              "batter": "Eknath Kerkar",
              "bowler": "LI Meriwala",
              "non_striker": "Shashank Singh",
              "runs": {
                "batter": 1,
                "extras": 0,
                "total": 1
              }
            },
            {
              "batter": "Shashank Singh",
              "bowler": "LI Meriwala",
              "non_striker": "Eknath Kerkar",
              "runs": {
                "batter": 1,
                "extras": 0,
                "total": 1
              }
            },
            {
              "batter": "Eknath Kerkar",
              "bowler": "LI Meriwala",
              "non_striker": "Shashank Singh",
              "runs": {
                "batter": 0,
                "extras": 0,
                "total": 0
              },
              "wickets": [
                {
                  "player_out": "Eknath Kerkar",
                  "kind": "lbw"
                }
              ]
            },
            {
              "batter": "Shashank Chandrakar",
              "bowler": "LI Meriwala",
              "non_striker": "Shashank Singh",
              "runs": {
                "batter": 1,
                "extras": 0,
                "total": 1
              }
            },
            {
              "batter": "Shashank Singh",
              "bowler": "LI Meriwala",
              "non_striker": "Shashank Chandrakar",
              "runs": {
                "batter": 2,
                "extras": 0,
                "total": 2
              }
            },
            {
              "batter": "Shashank Singh",
              "bowler": "LI Meriwala",
              "non_striker": "Shashank Chandrakar",
              "runs": {
                "batter": 0,
                "extras": 0,
                "total": 0
              },
              "wickets": [
                {
                  "player_out": "Shashank Singh",
                  "fielders": [
                    {
                      "name": "Jyotsnil Singh"
                    }
                  ],
                  "kind": "caught"
                }
              ]
            }
          ]
        },
        {
          "over": 18,
          "deliveries": [
            {
              "batter": "Shashank Chandrakar",
              "bowler": "A Sheth",
              "non_striker": "Sanjeet Desai",
              "replacements": {
                "match": [
                  {
                    "in": "Sanjeet Desai",
                    "out": "Harpreet Singh",
                    "team": "Chhattisgarh",
                    "reason": "impact_player"
                  }
                ]
              },
              "runs": {
                "batter": 4,
                "extras": 0,
                "total": 4
              }
            },
            {
              "batter": "Shashank Chandrakar",
              "bowler": "A Sheth",
              "extras": {
                "byes": 1
              },
              "non_striker": "Sanjeet Desai",
              "runs": {
                "batter": 0,
                "extras": 1,
                "total": 1
              }
            },
            {
              "batter": "Sanjeet Desai",
              "bowler": "A Sheth",
              "non_striker": "Shashank Chandrakar",
              "runs": {
                "batter": 1,
                "extras": 0,
                "total": 1
              }
            },
            {
              "batter": "Shashank Chandrakar",
              "bowler": "A Sheth",
              "non_striker": "Sanjeet Desai",
              "runs": {
                "batter": 0,
                "extras": 0,
                "total": 0
              }
            },
            {
              "batter": "Shashank Chandrakar",
              "bowler": "A Sheth",
              "extras": {
                "wides": 1
              },
              "non_striker": "Sanjeet Desai",
              "runs": {
                "batter": 0,
                "extras": 1,
                "total": 1
              }
            },
            {
              "batter": "Shashank Chandrakar",
              "bowler": "A Sheth",
              "non_striker": "Sanjeet Desai",
              "runs": {
                "batter": 2,
                "extras": 0,
                "total": 2
              }
            },
            {
              "batter": "Shashank Chandrakar",
              "bowler": "A Sheth",
              "non_striker": "Sanjeet Desai",
              "runs": {
                "batter": 0,
                "extras": 0,
                "total": 0
              },
              "wickets": [
                {
                  "player_out": "Shashank Chandrakar",
                  "fielders": [
                    {
                      "name": "LI Meriwala"
                    }
                  ],
                  "kind": "caught"
                }
              ]
            }
          ]
        },
        {
          "over": 19,
          "deliveries": [
            {
              "batter": "Sanjeet Desai",
              "bowler": "LI Meriwala",
              "non_striker": "SS Agarwal",
              "runs": {
                "batter": 2,
                "extras": 0,
                "total": 2
              }
            },
            {
              "batter": "Sanjeet Desai",
              "bowler": "LI Meriwala",
              "non_striker": "SS Agarwal",
              "runs": {
                "batter": 1,
                "extras": 0,
                "total": 1
              }
            },
            {
              "batter": "SS Agarwal",
              "bowler": "LI Meriwala",
              "non_striker": "Sanjeet Desai",
              "runs": {
                "batter": 1,
                "extras": 0,
                "total": 1
              }
            },
            {
              "batter": "Sanjeet Desai",
              "bowler": "LI Meriwala",
              "non_striker": "SS Agarwal",
              "runs": {
                "batter": 2,
                "extras": 0,
                "total": 2
              }
            },
            {
              "batter": "Sanjeet Desai",
              "bowler": "LI Meriwala",
              "non_striker": "SS Agarwal",
              "runs": {
                "batter": 1,
                "extras": 0,
                "total": 1
              }
            },
            {
              "batter": "SS Agarwal",
              "bowler": "LI Meriwala",
              "non_striker": "Sanjeet Desai",
              "runs": {
                "batter": 1,
                "extras": 0,
                "total": 1
              }
            }
          ]
        }
      ],
      "powerplays": [
        {
          "from": 0.1,
          "to": 5.6,
          "type": "mandatory"
        }
      ]
    },
    {
      "team": "Baroda",
      "overs": [
        {
          "over": 0,
          "deliveries": [
            {
              "batter": "Jyotsnil Singh",
              "bowler": "Sourabh Majumdar",
              "non_striker": "A Bharwad",
              "runs": {
                "batter": 0,
                "extras": 0,
                "total": 0
              }
            },
            {
              "batter": "Jyotsnil Singh",
              "bowler": "Sourabh Majumdar",
              "non_striker": "A Bharwad",
              "runs": {
                "batter": 0,
                "extras": 0,
                "total": 0
              }
            },
            {
              "batter": "Jyotsnil Singh",
              "bowler": "Sourabh Majumdar",
              "non_striker": "A Bharwad",
              "runs": {
                "batter": 0,
                "extras": 0,
                "total": 0
              }
            },
            {
              "batter": "Jyotsnil Singh",
              "bowler": "Sourabh Majumdar",
              "non_striker": "A Bharwad",
              "runs": {
                "batter": 0,
                "extras": 0,
                "total": 0
              }
            },
            {
              "batter": "Jyotsnil Singh",
              "bowler": "Sourabh Majumdar",
              "non_striker": "A Bharwad",
              "runs": {
                "batter": 1,
                "extras": 0,
                "total": 1
              }
            },
            {
              "batter": "A Bharwad",
              "bowler": "Sourabh Majumdar",
              "non_striker": "Jyotsnil Singh",
              "runs": {
                "batter": 0,
                "extras": 0,
                "total": 0
              }
            }
          ]
        },
        {
          "over": 1,
          "deliveries": [
            {
              "batter": "Jyotsnil Singh",
              "bowler": "PS Painkra",
              "non_striker": "A Bharwad",
              "runs": {
                "batter": 2,
                "extras": 0,
                "total": 2
              }
            },
            {
              "batter": "Jyotsnil Singh",
              "bowler": "PS Painkra",
              "non_striker": "A Bharwad",
              "runs": {
                "batter": 0,
                "extras": 0,
                "total": 0
              }
            },
            {
              "batter": "Jyotsnil Singh",
              "bowler": "PS Painkra",
              "non_striker": "A Bharwad",
              "runs": {
                "batter": 1,
                "extras": 0,
                "total": 1
              }
            },
            {
              "batter": "A Bharwad",
              "bowler": "PS Painkra",
              "non_striker": "Jyotsnil Singh",
              "runs": {
                "batter": 0,
                "extras": 0,
                "total": 0
              }
            },
            {
              "batter": "A Bharwad",
              "bowler": "PS Painkra",
              "non_striker": "Jyotsnil Singh",
              "runs": {
                "batter": 0,
                "extras": 0,
                "total": 0
              }
            },
            {
              "batter": "A Bharwad",
              "bowler": "PS Painkra",
              "extras": {
                "byes": 1
              },
              "non_striker": "Jyotsnil Singh",
              "runs": {
                "batter": 0,
                "extras": 1,
                "total": 1
              }
            }
          ]
        },
        {
          "over": 2,
          "deliveries": [
            {
              "batter": "A Bharwad",
              "bowler": "Sourabh Majumdar",
              "non_striker": "Jyotsnil Singh",
              "runs": {
                "batter": 0,
                "extras": 0,
                "total": 0
              }
            },
            {
              "batter": "A Bharwad",
              "bowler": "Sourabh Majumdar",
              "non_striker": "Jyotsnil Singh",
              "runs": {
                "batter": 0,
                "extras": 0,
                "total": 0
              }
            },
            {
              "batter": "A Bharwad",
              "bowler": "Sourabh Majumdar",
              "non_striker": "Jyotsnil Singh",
              "runs": {
                "batter": 1,
                "extras": 0,
                "total": 1
              }
            },
            {
              "batter": "Jyotsnil Singh",
              "bowler": "Sourabh Majumdar",
              "non_striker": "A Bharwad",
              "runs": {
                "batter": 4,
                "extras": 0,
                "total": 4
              }
            },
            {
              "batter": "Jyotsnil Singh",
              "bowler": "Sourabh Majumdar",
              "non_striker": "A Bharwad",
              "runs": {
                "batter": 1,
                "extras": 0,
                "total": 1
              }
            },
            {
              "batter": "A Bharwad",
              "bowler": "Sourabh Majumdar",
              "non_striker": "Jyotsnil Singh",
              "runs": {
                "batter": 0,
                "extras": 0,
                "total": 0
              }
            }
          ]
        },
        {
          "over": 3,
          "deliveries": [
            {
              "batter": "Jyotsnil Singh",
              "bowler": "Sumit Ruikar",
              "non_striker": "A Bharwad",
              "runs": {
                "batter": 0,
                "extras": 0,
                "total": 0
              }
            },
            {
              "batter": "Jyotsnil Singh",
              "bowler": "Sumit Ruikar",
              "non_striker": "A Bharwad",
              "runs": {
                "batter": 1,
                "extras": 0,
                "total": 1
              }
            },
            {
              "batter": "A Bharwad",
              "bowler": "Sumit Ruikar",
              "non_striker": "Jyotsnil Singh",
              "runs": {
                "batter": 1,
                "extras": 0,
                "total": 1
              }
            },
            {
              "batter": "Jyotsnil Singh",
              "bowler": "Sumit Ruikar",
              "non_striker": "A Bharwad",
              "runs": {
                "batter": 6,
                "extras": 0,
                "total": 6
              }
            },
            {
              "batter": "Jyotsnil Singh",
              "bowler": "Sumit Ruikar",
              "non_striker": "A Bharwad",
              "runs": {
                "batter": 6,
                "extras": 0,
                "total": 6
              }
            },
            {
              "batter": "Jyotsnil Singh",
              "bowler": "Sumit Ruikar",
              "non_striker": "A Bharwad",
              "runs": {
                "batter": 1,
                "extras": 0,
                "total": 1
              }
            }
          ]
        },
        {
          "over": 4,
          "deliveries": [
            {
              "batter": "Jyotsnil Singh",
              "bowler": "PS Painkra",
              "non_striker": "A Bharwad",
              "runs": {
                "batter": 1,
                "extras": 0,
                "total": 1
              }
            },
            {
              "batter": "A Bharwad",
              "bowler": "PS Painkra",
              "non_striker": "Jyotsnil Singh",
              "runs": {
                "batter": 0,
                "extras": 0,
                "total": 0
              }
            },
            {
              "batter": "A Bharwad",
              "bowler": "PS Painkra",
              "non_striker": "Jyotsnil Singh",
              "runs": {
                "batter": 6,
                "extras": 0,
                "total": 6
              }
            },
            {
              "batter": "A Bharwad",
              "bowler": "PS Painkra",
              "non_striker": "Jyotsnil Singh",
              "runs": {
                "batter": 1,
                "extras": 0,
                "total": 1
              }
            },
            {
              "batter": "Jyotsnil Singh",
              "bowler": "PS Painkra",
              "non_striker": "A Bharwad",
              "runs": {
                "batter": 0,
                "extras": 0,
                "total": 0
              }
            },
            {
              "batter": "Jyotsnil Singh",
              "bowler": "PS Painkra",
              "non_striker": "A Bharwad",
              "runs": {
                "batter": 1,
                "extras": 0,
                "total": 1
              }
            }
          ]
        },
        {
          "over": 5,
          "deliveries": [
            {
              "batter": "Jyotsnil Singh",
              "bowler": "Sourabh Majumdar",
              "non_striker": "A Bharwad",
              "runs": {
                "batter": 0,
                "extras": 0,
                "total": 0
              }
            },
            {
              "batter": "Jyotsnil Singh",
              "bowler": "Sourabh Majumdar",
              "non_striker": "A Bharwad",
              "runs": {
                "batter": 1,
                "extras": 0,
                "total": 1
              }
            },
            {
              "batter": "A Bharwad",
              "bowler": "Sourabh Majumdar",
              "non_striker": "Jyotsnil Singh",
              "runs": {
                "batter": 1,
                "extras": 0,
                "total": 1
              }
            },
            {
              "batter": "Jyotsnil Singh",
              "bowler": "Sourabh Majumdar",
              "non_striker": "A Bharwad",
              "runs": {
                "batter": 1,
                "extras": 0,
                "total": 1
              }
            },
            {
              "batter": "A Bharwad",
              "bowler": "Sourabh Majumdar",
              "non_striker": "Jyotsnil Singh",
              "runs": {
                "batter": 1,
                "extras": 0,
                "total": 1
              }
            },
            {
              "batter": "Jyotsnil Singh",
              "bowler": "Sourabh Majumdar",
              "non_striker": "A Bharwad",
              "runs": {
                "batter": 4,
                "extras": 0,
                "total": 4
              }
            }
          ]
        },
        {
          "over": 6,
          "deliveries": [
            {
              "batter": "A Bharwad",
              "bowler": "SS Agarwal",
              "non_striker": "Jyotsnil Singh",
              "runs": {
                "batter": 0,
                "extras": 0,
                "total": 0
              }
            },
            {
              "batter": "A Bharwad",
              "bowler": "SS Agarwal",
              "non_striker": "Jyotsnil Singh",
              "runs": {
                "batter": 1,
                "extras": 0,
                "total": 1
              }
            },
            {
              "batter": "Jyotsnil Singh",
              "bowler": "SS Agarwal",
              "non_striker": "A Bharwad",
              "runs": {
                "batter": 0,
                "extras": 0,
                "total": 0
              }
            },
            {
              "batter": "Jyotsnil Singh",
              "bowler": "SS Agarwal",
              "non_striker": "A Bharwad",
              "runs": {
                "batter": 2,
                "extras": 0,
                "total": 2
              }
            },
            {
              "batter": "Jyotsnil Singh",
              "bowler": "SS Agarwal",
              "non_striker": "A Bharwad",
              "runs": {
                "batter": 1,
                "extras": 0,
                "total": 1
              }
            },
            {
              "batter": "A Bharwad",
              "bowler": "SS Agarwal",
              "non_striker": "Jyotsnil Singh",
              "runs": {
                "batter": 1,
                "extras": 0,
                "total": 1
              }
            }
          ]
        },
        {
          "over": 7,
          "deliveries": [
            {
              "batter": "A Bharwad",
              "bowler": "Ajay Mandal",
              "non_striker": "Jyotsnil Singh",
              "runs": {
                "batter": 1,
                "extras": 0,
                "total": 1
              }
            },
            {
              "batter": "Jyotsnil Singh",
              "bowler": "Ajay Mandal",
              "non_striker": "A Bharwad",
              "runs": {
                "batter": 1,
                "extras": 0,
                "total": 1
              }
            },
            {
              "batter": "A Bharwad",
              "bowler": "Ajay Mandal",
              "non_striker": "Jyotsnil Singh",
              "runs": {
                "batter": 1,
                "extras": 0,
                "total": 1
              }
            },
            {
              "batter": "Jyotsnil Singh",
              "bowler": "Ajay Mandal",
              "non_striker": "A Bharwad",
              "runs": {
                "batter": 0,
                "extras": 0,
                "total": 0
              }
            },
            {
              "batter": "Jyotsnil Singh",
              "bowler": "Ajay Mandal",
              "non_striker": "A Bharwad",
              "runs": {
                "batter": 1,
                "extras": 0,
                "total": 1
              }
            },
            {
              "batter": "A Bharwad",
              "bowler": "Ajay Mandal",
              "non_striker": "Jyotsnil Singh",
              "runs": {
                "batter": 0,
                "extras": 0,
                "total": 0
              }
            }
          ]
        },
        {
          "over": 8,
          "deliveries": [
            {
              "batter": "Jyotsnil Singh",
              "bowler": "SS Agarwal",
              "non_striker": "A Bharwad",
              "runs": {
                "batter": 4,
                "extras": 0,
                "total": 4
              }
            },
            {
              "batter": "Jyotsnil Singh",
              "bowler": "SS Agarwal",
              "non_striker": "A Bharwad",
              "runs": {
                "batter": 4,
                "extras": 0,
                "total": 4
              }
            },
            {
              "batter": "Jyotsnil Singh",
              "bowler": "SS Agarwal",
              "non_striker": "A Bharwad",
              "runs": {
                "batter": 1,
                "extras": 0,
                "total": 1
              }
            },
            {
              "batter": "A Bharwad",
              "bowler": "SS Agarwal",
              "non_striker": "Jyotsnil Singh",
              "runs": {
                "batter": 0,
                "extras": 0,
                "total": 0
              }
            },
            {
              "batter": "A Bharwad",
              "bowler": "SS Agarwal",
              "non_striker": "Jyotsnil Singh",
              "runs": {
                "batter": 1,
                "extras": 0,
                "total": 1
              }
            },
            {
              "batter": "Jyotsnil Singh",
              "bowler": "SS Agarwal",
              "non_striker": "A Bharwad",
              "runs": {
                "batter": 0,
                "extras": 0,
                "total": 0
              }
            }
          ]
        },
        {
          "over": 9,
          "deliveries": [
            {
              "batter": "A Bharwad",
              "bowler": "Ajay Mandal",
              "non_striker": "Jyotsnil Singh",
              "runs": {
                "batter": 1,
                "extras": 0,
                "total": 1
              }
            },
            {
              "batter": "Jyotsnil Singh",
              "bowler": "Ajay Mandal",
              "non_striker": "A Bharwad",
              "runs": {
                "batter": 0,
                "extras": 0,
                "total": 0
              },
              "wickets": [
                {
                  "player_out": "Jyotsnil Singh",
                  "fielders": [
                    {
                      "name": "Shashank Chandrakar"
                    }
                  ],
                  "kind": "caught"
                }
              ]
            },
            {
              "batter": "KH Pandya",
              "bowler": "Ajay Mandal",
              "non_striker": "A Bharwad",
              "runs": {
                "batter": 1,
                "extras": 0,
                "total": 1
              }
            },
            {
              "batter": "A Bharwad",
              "bowler": "Ajay Mandal",
              "non_striker": "KH Pandya",
              "runs": {
                "batter": 1,
                "extras": 0,
                "total": 1
              }
            },
            {
              "batter": "KH Pandya",
              "bowler": "Ajay Mandal",
              "non_striker": "A Bharwad",
              "runs": {
                "batter": 1,
                "extras": 0,
                "total": 1
              }
            },
            {
              "batter": "A Bharwad",
              "bowler": "Ajay Mandal",
              "non_striker": "KH Pandya",
              "runs": {
                "batter": 0,
                "extras": 0,
                "total": 0
              },
              "wickets": [
                {
                  "player_out": "A Bharwad",
                  "kind": "bowled"
                }
              ]
            }
          ]
        },
        {
          "over": 10,
          "deliveries": [
            {
              "batter": "KH Pandya",
              "bowler": "Sumit Ruikar",
              "non_striker": "Vishnu Solanki",
              "runs": {
                "batter": 0,
                "extras": 0,
                "total": 0
              }
            },
            {
              "batter": "KH Pandya",
              "bowler": "Sumit Ruikar",
              "non_striker": "Vishnu Solanki",
              "runs": {
                "batter": 1,
                "extras": 0,
                "total": 1
              }
            },
            {
              "batter": "Vishnu Solanki",
              "bowler": "Sumit Ruikar",
              "non_striker": "KH Pandya",
              "runs": {
                "batter": 0,
                "extras": 0,
                "total": 0
              }
            },
            {
              "batter": "Vishnu Solanki",
              "bowler": "Sumit Ruikar",
              "non_striker": "KH Pandya",
              "runs": {
                "batter": 1,
                "extras": 0,
                "total": 1
              }
            },
            {
              "batter": "KH Pandya",
              "bowler": "Sumit Ruikar",
              "non_striker": "Vishnu Solanki",
              "runs": {
                "batter": 0,
                "extras": 0,
                "total": 0
              }
            },
            {
              "batter": "KH Pandya",
              "bowler": "Sumit Ruikar",
              "non_striker": "Vishnu Solanki",
              "runs": {
                "batter": 1,
                "extras": 0,
                "total": 1
              }
            }
          ]
        },
        {
          "over": 11,
          "deliveries": [
            {
              "batter": "KH Pandya",
              "bowler": "Ajay Mandal",
              "non_striker": "Vishnu Solanki",
              "runs": {
                "batter": 0,
                "extras": 0,
                "total": 0
              }
            },
            {
              "batter": "KH Pandya",
              "bowler": "Ajay Mandal",
              "non_striker": "Vishnu Solanki",
              "runs": {
                "batter": 1,
                "extras": 0,
                "total": 1
              }
            },
            {
              "batter": "Vishnu Solanki",
              "bowler": "Ajay Mandal",
              "non_striker": "KH Pandya",
              "runs": {
                "batter": 2,
                "extras": 0,
                "total": 2
              }
            },
            {
              "batter": "Vishnu Solanki",
              "bowler": "Ajay Mandal",
              "non_striker": "KH Pandya",
              "runs": {
                "batter": 1,
                "extras": 0,
                "total": 1
              }
            },
            {
              "batter": "KH Pandya",
              "bowler": "Ajay Mandal",
              "non_striker": "Vishnu Solanki",
              "runs": {
                "batter": 1,
                "extras": 0,
                "total": 1
              }
            },
            {
              "batter": "Vishnu Solanki",
              "bowler": "Ajay Mandal",
              "non_striker": "KH Pandya",
              "runs": {
                "batter": 2,
                "extras": 0,
                "total": 2
              }
            }
          ]
        },
        {
          "over": 12,
          "deliveries": [
            {
              "batter": "KH Pandya",
              "bowler": "Sumit Ruikar",
              "non_striker": "Vishnu Solanki",
              "runs": {
                "batter": 1,
                "extras": 0,
                "total": 1
              }
            },
            {
              "batter": "Vishnu Solanki",
              "bowler": "Sumit Ruikar",
              "non_striker": "KH Pandya",
              "runs": {
                "batter": 1,
                "extras": 0,
                "total": 1
              }
            },
            {
              "batter": "KH Pandya",
              "bowler": "Sumit Ruikar",
              "non_striker": "Vishnu Solanki",
              "runs": {
                "batter": 1,
                "extras": 0,
                "total": 1
              }
            },
            {
              "batter": "Vishnu Solanki",
              "bowler": "Sumit Ruikar",
              "non_striker": "KH Pandya",
              "runs": {
                "batter": 0,
                "extras": 0,
                "total": 0
              }
            },
            {
              "batter": "Vishnu Solanki",
              "bowler": "Sumit Ruikar",
              "non_striker": "KH Pandya",
              "runs": {
                "batter": 4,
                "extras": 0,
                "total": 4
              }
            },
            {
              "batter": "Vishnu Solanki",
              "bowler": "Sumit Ruikar",
              "non_striker": "KH Pandya",
              "runs": {
                "batter": 1,
                "extras": 0,
                "total": 1
              }
            }
          ]
        },
        {
          "over": 13,
          "deliveries": [
            {
              "batter": "Vishnu Solanki",
              "bowler": "Ajay Mandal",
              "non_striker": "KH Pandya",
              "runs": {
                "batter": 1,
                "extras": 0,
                "total": 1
              }
            },
            {
              "batter": "KH Pandya",
              "bowler": "Ajay Mandal",
              "non_striker": "Vishnu Solanki",
              "runs": {
                "batter": 2,
                "extras": 0,
                "total": 2
              }
            },
            {
              "batter": "KH Pandya",
              "bowler": "Ajay Mandal",
              "non_striker": "Vishnu Solanki",
              "runs": {
                "batter": 1,
                "extras": 0,
                "total": 1
              }
            },
            {
              "batter": "Vishnu Solanki",
              "bowler": "Ajay Mandal",
              "non_striker": "KH Pandya",
              "runs": {
                "batter": 1,
                "extras": 0,
                "total": 1
              }
            },
            {
              "batter": "KH Pandya",
              "bowler": "Ajay Mandal",
              "non_striker": "Vishnu Solanki",
              "runs": {
                "batter": 0,
                "extras": 0,
                "total": 0
              }
            },
            {
              "batter": "KH Pandya",
              "bowler": "Ajay Mandal",
              "non_striker": "Vishnu Solanki",
              "runs": {
                "batter": 2,
                "extras": 0,
                "total": 2
              }
            }
          ]
        },
        {
          "over": 14,
          "deliveries": [
            {
              "batter": "Vishnu Solanki",
              "bowler": "Sumit Ruikar",
              "non_striker": "KH Pandya",
              "runs": {
                "batter": 1,
                "extras": 0,
                "total": 1
              }
            },
            {
              "batter": "KH Pandya",
              "bowler": "Sumit Ruikar",
              "non_striker": "Vishnu Solanki",
              "runs": {
                "batter": 4,
                "extras": 0,
                "total": 4
              }
            },
            {
              "batter": "KH Pandya",
              "bowler": "Sumit Ruikar",
              "non_striker": "Vishnu Solanki",
              "runs": {
                "batter": 6,
                "extras": 0,
                "total": 6
              }
            },
            {
              "batter": "KH Pandya",
              "bowler": "Sumit Ruikar",
              "non_striker": "Vishnu Solanki",
              "runs": {
                "batter": 0,
                "extras": 0,
                "total": 0
              }
            },
            {
              "batter": "KH Pandya",
              "bowler": "Sumit Ruikar",
              "non_striker": "Vishnu Solanki",
              "runs": {
                "batter": 1,
                "extras": 0,
                "total": 1
              }
            },
            {
              "batter": "Vishnu Solanki",
              "bowler": "Sumit Ruikar",
              "non_striker": "KH Pandya",
              "runs": {
                "batter": 1,
                "extras": 0,
                "total": 1
              }
            }
          ]
        },
        {
          "over": 15,
          "deliveries": [
            {
              "batter": "Vishnu Solanki",
              "bowler": "Shashank Singh",
              "non_striker": "KH Pandya",
              "runs": {
                "batter": 2,
                "extras": 0,
                "total": 2
              }
            },
            {
              "batter": "Vishnu Solanki",
              "bowler": "Shashank Singh",
              "non_striker": "KH Pandya",
              "runs": {
                "batter": 1,
                "extras": 0,
                "total": 1
              }
            },
            {
              "batter": "KH Pandya",
              "bowler": "Shashank Singh",
              "non_striker": "Vishnu Solanki",
              "runs": {
                "batter": 2,
                "extras": 0,
                "total": 2
              }
            },
            {
              "batter": "KH Pandya",
              "bowler": "Shashank Singh",
              "non_striker": "Vishnu Solanki",
              "runs": {
                "batter": 1,
                "extras": 0,
                "total": 1
              }
            },
            {
              "batter": "Vishnu Solanki",
              "bowler": "Shashank Singh",
              "non_striker": "KH Pandya",
              "runs": {
                "batter": 4,
                "extras": 0,
                "total": 4
              }
            },
            {
              "batter": "Vishnu Solanki",
              "bowler": "Shashank Singh",
              "non_striker": "KH Pandya",
              "runs": {
                "batter": 1,
                "extras": 0,
                "total": 1
              }
            }
          ]
        },
        {
          "over": 16,
          "deliveries": [
            {
              "batter": "Vishnu Solanki",
              "bowler": "PS Painkra",
              "non_striker": "KH Pandya",
              "runs": {
                "batter": 1,
                "extras": 0,
                "total": 1
              }
            },
            {
              "batter": "KH Pandya",
              "bowler": "PS Painkra",
              "non_striker": "Vishnu Solanki",
              "runs": {
                "batter": 0,
                "extras": 0,
                "total": 0
              }
            },
            {
              "batter": "KH Pandya",
              "bowler": "PS Painkra",
              "extras": {
                "legbyes": 1
              },
              "non_striker": "Vishnu Solanki",
              "runs": {
                "batter": 0,
                "extras": 1,
                "total": 1
              }
            },
            {
              "batter": "Vishnu Solanki",
              "bowler": "PS Painkra",
              "non_striker": "KH Pandya",
              "runs": {
                "batter": 0,
                "extras": 0,
                "total": 0
              }
            },
            {
              "batter": "Vishnu Solanki",
              "bowler": "PS Painkra",
              "non_striker": "KH Pandya",
              "runs": {
                "batter": 2,
                "extras": 0,
                "total": 2
              }
            },
            {
              "batter": "Vishnu Solanki",
              "bowler": "PS Painkra",
              "non_striker": "KH Pandya",
              "runs": {
                "batter": 0,
                "extras": 0,
                "total": 0
              },
              "wickets": [
                {
                  "player_out": "Vishnu Solanki",
                  "fielders": [
                    {
                      "name": "Sumit Ruikar"
                    }
                  ],
                  "kind": "caught"
                }
              ]
            }
          ]
        },
        {
          "over": 17,
          "deliveries": [
            {
              "batter": "KH Pandya",
              "bowler": "Sourabh Majumdar",
              "non_striker": "Bhanu Pania",
              "runs": {
                "batter": 2,
                "extras": 0,
                "total": 2
              }
            },
            {
              "batter": "KH Pandya",
              "bowler": "Sourabh Majumdar",
              "non_striker": "Bhanu Pania",
              "runs": {
                "batter": 0,
                "extras": 0,
                "total": 0
              }
            },
            {
              "batter": "KH Pandya",
              "bowler": "Sourabh Majumdar",
              "non_striker": "Bhanu Pania",
              "runs": {
                "batter": 2,
                "extras": 0,
                "total": 2
              }
            },
            {
              "batter": "KH Pandya",
              "bowler": "Sourabh Majumdar",
              "non_striker": "Bhanu Pania",
              "runs": {
                "batter": 1,
                "extras": 0,
                "total": 1
              }
            },
            {
              "batter": "Bhanu Pania",
              "bowler": "Sourabh Majumdar",
              "extras": {
                "wides": 1
              },
              "non_striker": "KH Pandya",
              "runs": {
                "batter": 0,
                "extras": 1,
                "total": 1
              }
            },
            {
              "batter": "Bhanu Pania",
              "bowler": "Sourabh Majumdar",
              "non_striker": "KH Pandya",
              "runs": {
                "batter": 1,
                "extras": 0,
                "total": 1
              }
            },
            {
              "batter": "KH Pandya",
              "bowler": "Sourabh Majumdar",
              "non_striker": "Bhanu Pania",
              "runs": {
                "batter": 1,
                "extras": 0,
                "total": 1
              }
            }
          ]
        },
        {
          "over": 18,
          "deliveries": [
            {
              "batter": "KH Pandya",
              "bowler": "PS Painkra",
              "non_striker": "Bhanu Pania",
              "runs": {
                "batter": 4,
                "extras": 0,
                "total": 4
              }
            },
            {
              "batter": "KH Pandya",
              "bowler": "PS Painkra",
              "non_striker": "Bhanu Pania",
              "runs": {
                "batter": 1,
                "extras": 0,
                "total": 1
              }
            }
          ]
        }
      ],
      "powerplays": [
        {
          "from": 0.1,
          "to": 5.6,
          "type": "mandatory"
        }
      ],
      "target": {
        "overs": 20,
        "runs": 132
      }
    }
  ]
}